lexar/__init__.py
lexar/pipeline.py
lexar-0.1.0.dist-info/licenses/LICENSE
lexar-0.1.0.dist-info/METADATA
lexar-0.1.0.dist-info/WHEEL
lexar-0.1.0.dist-info/top_level.txt
lexar-0.1.0.dist-info/RECORD
