Metadata-Version: 2.4
Name: lexar
Version: 0.1.0
Summary: A spaCy-based Named Entity Recognition (NER) pipeline optimized for legal documents.
Author-email: Tvisha Majithia <tvishamajithia13@gmail.com>
License: MIT License
Classifier: Development Status :: 3 - Alpha
Classifier: Intended Audience :: Developers
Classifier: Intended Audience :: Legal Industry
Classifier: License :: OSI Approved :: MIT License
Classifier: Programming Language :: Python :: 3
Classifier: Programming Language :: Python :: 3.8
Classifier: Programming Language :: Python :: 3.9
Classifier: Programming Language :: Python :: 3.10
Classifier: Programming Language :: Python :: 3.11
Classifier: Topic :: Scientific/Engineering :: Artificial Intelligence
Classifier: Topic :: Text Processing :: Linguistic
Requires-Python: >=3.8
License-File: LICENSE
Requires-Dist: spacy>=3.0.0
Requires-Dist: en_core_web_sm; python_version < "3.11"
Dynamic: license-file
